gym_display_advertising/__init__.py
gym_display_advertising/data.py
gym_display_advertising/envs/__init__.py
gym_display_advertising/envs/display_advertising_env.py
gym_display_advertising/envs/static_display_advertising_env.py
tests/__init__.py
tests/test_display_advertising.py
tests/test_processed_ipinyou_data.py
tests/test_static_display_advertising.py
gym_display_advertising-0.0.1.dist-info/LICENSE
gym_display_advertising-0.0.1.dist-info/METADATA
gym_display_advertising-0.0.1.dist-info/WHEEL
gym_display_advertising-0.0.1.dist-info/top_level.txt
gym_display_advertising-0.0.1.dist-info/RECORD
