Metadata-Version: 2.1
Name: gym-display-advertising
Version: 0.0.1
Summary: An OpenAI Gym for Display Advertisment Reinforcement Learning
Home-page: https://gitlab.com/winderresearch/gym-display-advertising
Author: Phil Winder
Author-email: phil@winderresearch.com
License: MIT
Platform: UNKNOWN
Requires-Dist: gym (>=0.12.5)
Requires-Dist: pandas (>=0.18.1)
